jiffyCodec/__init__.py
jiffyCodec/jiffyCodec.py
jiffyCodec-0.3.1.dist-info/LICENSE
jiffyCodec-0.3.1.dist-info/METADATA
jiffyCodec-0.3.1.dist-info/WHEEL
jiffyCodec-0.3.1.dist-info/top_level.txt
jiffyCodec-0.3.1.dist-info/RECORD
