Metadata-Version: 2.1
Name: jiffyCodec
Version: 0.3.1
Summary: jiffyCodec: a fast, lossless SIMD compression codec for LiDAR streams
Author-email: Jeff Ford <jsford64@gmail.com>, Jordan Ford <jsford94@gmail.com>
Project-URL: Homepage, https://github.com/jsford64/jiffy-compression
Classifier: Programming Language :: Python :: 3
Classifier: License :: OSI Approved :: Apache Software License
Classifier: Operating System :: OS Independent
Requires-Python: >=3.10
License-File: LICENSE
Requires-Dist: zstandard
Requires-Dist: numpy
Requires-Dist: pyfastpfor ; platform_machine == "x86_64" and sys_platform != "darwin"
